gwpd/__init__.py
gwpd/pdtb.py
gwpd/pdvw.py
gwpd_genwch-0.0.5.dist-info/LICENSE
gwpd_genwch-0.0.5.dist-info/METADATA
gwpd_genwch-0.0.5.dist-info/WHEEL
gwpd_genwch-0.0.5.dist-info/top_level.txt
gwpd_genwch-0.0.5.dist-info/RECORD
