Metadata-Version: 2.1
Name: gwpd-genwch
Version: 0.0.5
Summary: gwpd
Home-page: https://github.com/genwch/gwpd
Author: genwch
Author-email: 
License: UNKNOWN
Platform: UNKNOWN
Classifier: Programming Language :: Python :: 3
Classifier: License :: OSI Approved :: MIT License
Classifier: Operating System :: OS Independent
Requires-Python: >=3.7
Requires-Dist: gwcomm-genwch
Requires-Dist: Werkzeug (==0.16.1)
Requires-Dist: pandas (==1.2.1)
Requires-Dist: pyarrow (==0.16.0)
